{
  "generated_at_utc": "2026-07-13T22:14:56Z",
  "generated_at_taipei": "2026-07-14 06:14:56+08:00",
  "taipei_date": "2026-07-14",
  "summary": {
    "total": 23,
    "success": 23,
    "missing": 0
  },
  "quotes": {
    "台股加權": {
      "name": "台股加權",
      "status": "ok",
      "source": "twse_index",
      "date": "2026-07-13",
      "close": 45380.52,
      "prev": 45354.61,
      "pct": 0.06
    },
    "台積電(2330)": {
      "name": "台積電(2330)",
      "status": "ok",
      "source": "yahoo",
      "date": "2026-07-13",
      "close": 2440.0,
      "prev": 2415.0,
      "pct": 1.04
    },
    "玉山金(2884)": {
      "name": "玉山金(2884)",
      "status": "ok",
      "source": "yahoo",
      "date": "2026-07-13",
      "close": 34.6,
      "prev": 34.75,
      "pct": -0.43
    },
    "兆豐金(2886)": {
      "name": "兆豐金(2886)",
      "status": "ok",
      "source": "yahoo",
      "date": "2026-07-13",
      "close": 47.0,
      "prev": 46.7,
      "pct": 0.64
    },
    "元大金(2885)": {
      "name": "元大金(2885)",
      "status": "ok",
      "source": "yahoo",
      "date": "2026-07-13",
      "close": 68.3,
      "prev": 68.3,
      "pct": 0.0
    },
    "台達電(2308)": {
      "name": "台達電(2308)",
      "status": "ok",
      "source": "yahoo",
      "date": "2026-07-13",
      "close": 1890.0,
      "prev": 1880.0,
      "pct": 0.53
    },
    "廣達(2382)": {
      "name": "廣達(2382)",
      "status": "ok",
      "source": "yahoo",
      "date": "2026-07-13",
      "close": 378.0,
      "prev": 373.5,
      "pct": 1.2
    },
    "健策(3653)": {
      "name": "健策(3653)",
      "status": "ok",
      "source": "yahoo",
      "date": "2026-07-13",
      "close": 3195.0,
      "prev": 3205.0,
      "pct": -0.31
    },
    "群聯(8299)": {
      "name": "群聯(8299)",
      "status": "ok",
      "source": "yahoo",
      "date": "2026-07-13",
      "close": 2170.0,
      "prev": 2220.0,
      "pct": -2.25
    },
    "S&P500": {
      "name": "S&P500",
      "status": "ok",
      "source": "yahoo",
      "date": "2026-07-13",
      "close": 7515.3398,
      "prev": 7575.3901,
      "pct": -0.79
    },
    "那指": {
      "name": "那指",
      "status": "ok",
      "source": "yahoo",
      "date": "2026-07-13",
      "close": 25873.1758,
      "prev": 26281.6094,
      "pct": -1.55
    },
    "費半": {
      "name": "費半",
      "status": "ok",
      "source": "yahoo",
      "date": "2026-07-13",
      "close": 12347.7832,
      "prev": 12967.1602,
      "pct": -4.78
    },
    "NVDA": {
      "name": "NVDA",
      "status": "ok",
      "source": "yahoo",
      "date": "2026-07-13",
      "close": 203.53,
      "prev": 210.96,
      "pct": -3.52
    },
    "MU": {
      "name": "MU",
      "status": "ok",
      "source": "yahoo",
      "date": "2026-07-13",
      "close": 937.0,
      "prev": 979.3,
      "pct": -4.32
    },
    "GOOG": {
      "name": "GOOG",
      "status": "ok",
      "source": "yahoo",
      "date": "2026-07-13",
      "close": 350.67,
      "prev": 355.03,
      "pct": -1.23
    },
    "PLTR": {
      "name": "PLTR",
      "status": "ok",
      "source": "yahoo",
      "date": "2026-07-13",
      "close": 130.04,
      "prev": 126.79,
      "pct": 2.56
    },
    "SPY": {
      "name": "SPY",
      "status": "ok",
      "source": "yahoo",
      "date": "2026-07-13",
      "close": 749.17,
      "prev": 754.95,
      "pct": -0.77
    },
    "QQQ": {
      "name": "QQQ",
      "status": "ok",
      "source": "yahoo",
      "date": "2026-07-13",
      "close": 711.74,
      "prev": 725.51,
      "pct": -1.9
    },
    "VTI": {
      "name": "VTI",
      "status": "ok",
      "source": "yahoo",
      "date": "2026-07-13",
      "close": 369.78,
      "prev": 372.69,
      "pct": -0.78
    },
    "UUUU": {
      "name": "UUUU",
      "status": "ok",
      "source": "yahoo",
      "date": "2026-07-13",
      "close": 13.05,
      "prev": 13.58,
      "pct": -3.9
    },
    "美債10Y": {
      "name": "美債10Y",
      "status": "ok",
      "source": "yahoo",
      "date": "2026-07-13",
      "close": 4.609,
      "prev": 4.569,
      "pct": 0.88
    },
    "美元指數": {
      "name": "美元指數",
      "status": "ok",
      "source": "yahoo",
      "date": "2026-07-13",
      "close": 101.277,
      "prev": 100.97,
      "pct": 0.3
    },
    "VIX": {
      "name": "VIX",
      "status": "ok",
      "source": "yahoo",
      "date": "2026-07-13",
      "close": 17.16,
      "prev": 15.03,
      "pct": 14.17
    }
  },
  "missing_names": []
}